authorityspoke/__init__.py
authorityspoke/courts.py
authorityspoke/decisions.py
authorityspoke/facts.py
authorityspoke/holdings.py
authorityspoke/opinions.py
authorityspoke/procedures.py
authorityspoke/rules.py
authorityspoke/io/__init__.py
authorityspoke/io/fake_enactments.py
authorityspoke/io/filepaths.py
authorityspoke/io/loaders.py
authorityspoke/io/name_index.py
authorityspoke/io/nesting.py
authorityspoke/io/readers.py
authorityspoke/io/text_expansion.py
authorityspoke/io/writers.py
AuthoritySpoke-0.10.0.dist-info/METADATA
AuthoritySpoke-0.10.0.dist-info/WHEEL
AuthoritySpoke-0.10.0.dist-info/top_level.txt
AuthoritySpoke-0.10.0.dist-info/RECORD
