Metadata-Version: 2.2
Name: AuthoritySpoke
Version: 0.10.0
Summary: legal authority automation
Home-page: https://github.com/mscarey/authorityspoke
Author: Matthew Carey
Author-email: matt@authorityspoke.com
Project-URL: Bug Tracker, https://github.com/mscarey/authorityspoke/issues
Project-URL: Documentation, https://authorityspoke.readthedocs.io/en/latest/
Classifier: Development Status :: 4 - Beta
Classifier: Intended Audience :: Legal Industry
Classifier: License :: Free To Use But Restricted
Classifier: Programming Language :: Python :: 3.11
Classifier: Programming Language :: Python :: 3.12
Classifier: Operating System :: OS Independent
Classifier: Natural Language :: English
Requires-Python: >=3.11
Requires-Dist: lxml==4.9.1
Requires-Dist: anchorpoint~=0.7.0
Requires-Dist: eyecite~=2.3.4
Requires-Dist: justopinion~=0.2.5
Requires-Dist: legislice~=0.7.0
Requires-Dist: nettlesome~=0.6.1
Requires-Dist: pint>=0.15
Requires-Dist: pydantic
Requires-Dist: python-dotenv
Requires-Dist: python-ranges~=0.2.1
Requires-Dist: python-slugify
Requires-Dist: pyyaml
Requires-Dist: requests
Requires-Dist: roman
Requires-Dist: sympy>=1.7.1
Dynamic: author
Dynamic: author-email
Dynamic: classifier
Dynamic: description
Dynamic: description-content-type
Dynamic: home-page
Dynamic: project-url
Dynamic: requires-dist
Dynamic: requires-python
Dynamic: summary
